{
  "log json stringify": {
    "prefix": ";log-json-stringify",
    "body": ["console.log(JSON.stringify($1, null, ${2:2}))$0"]
  },
  "export interface": {
    "prefix": ";export-interface",
    "body": ["export interface $1 {", "\t$2", "}"]
  },
  "import statement": {
    "prefix": ";import",
    "body": "import { $2 } from '$1'"
  },
  "log via JSON.parse(JSON.stringify())": {
    "prefix": ";ls",
    "body": "console.log($2JSON.parse(JSON.stringify($1)))"
  },
  "next.js meta tag with color schema dark light": {
    "prefix": ";nextjs-color-schema-dark-light",
    "description": "The page supports both dark and light color schemes, and the page author prefers dark.",
    "body": ["export const viewport: Viewport$0 = {", "  colorScheme: 'dark light',", "}"]
  },
  "next.js meta tag with color schema light dark": {
    "prefix": ";nextjs-color-schema-light-dark",
    "description": "The page supports both dark and light color schemes, and the page author prefers light.",
    "body": ["export const viewport: Viewport$0 = {", "  colorScheme: 'light dark',", "}"]
  },

  "just placed as the last item to conserve the last snippets' tailing comma": {
    "prefix": "ɵ",
    "body": ""
  }
}
